codertools/queryer/__init__.py
codertools/queryer/build.py
codertools/queryer/load.py
codertools/queryer/reader.py
codertools/reader/__init__.py
codertools/reader/function.py
codertools/reader/reader.py
codertools/reader/utils.py
codertools-0.1.5.dist-info/METADATA
codertools-0.1.5.dist-info/WHEEL
codertools-0.1.5.dist-info/top_level.txt
codertools-0.1.5.dist-info/RECORD
